{
  "generated_at": "2026-07-12T16:44:59Z",
  "tiktok": [],
  "instagram": [],
  "reddit": [],
  "google_trends": [
    {
      "id": "bd7180dd160a0b97",
      "query": "minecraft cushions",
      "value": "+21550%"
    },
    {
      "id": "85c6d489bd9fc899",
      "query": "minecraft cushion update",
      "value": "+14450%"
    },
    {
      "id": "7dd8f719cafb3788",
      "query": "cushion minecraft",
      "value": "+7150%"
    },
    {
      "id": "2dc1f6968235b4c4",
      "query": "are cushions in minecraft bedrock",
      "value": "+5900%"
    },
    {
      "id": "ff2eab54e501e6a4",
      "query": "minecraft new update",
      "value": "+170%"
    },
    {
      "id": "b1d0051f6cd631fe",
      "query": "dappled forest minecraft",
      "value": "+110%"
    },
    {
      "id": "6710c58dcd315d00",
      "query": "minecraft scholarship",
      "value": "+70%"
    },
    {
      "id": "b059bce9b56a5156",
      "query": "minecraft update",
      "value": "+70%"
    }
  ]
}